{
	"song": {
		"player1": "bf-henry",
		"events": [
			[
				6400,
				[
					[
						"Henry Event",
						"begin",
						""
					]
				]
			],
			[
				102854.545454545,
				[
					[
						"Hide UI",
						"on",
						"1"
					]
				]
			],
			[
				103127.272727273,
				[
					[
						"Henry Event",
						"hide",
						""
					]
				]
			],
			[
				106763.636363636,
				[
					[
						"Henry Event",
						"add baby",
						""
					]
				]
			],
			[
				107400,
				[
					[
						"Change Scroll Speed",
						"1.2",
						""
					]
				]
			],
			[
				107490.909090909,
				[
					[
						"Hide UI",
						"off",
						"1"
					]
				]
			],
			[
				155490.909090909,
				[
					[
						"Henry Event",
						"remove baby",
						""
					]
				]
			],
			[
				156127.272727273,
				[
					[
						"Play Animation",
						"death",
						"dad"
					]
				]
			],
			[
				156218.181818182,
				[
					[
						"Henry Event",
						"reveal",
						""
					]
				]
			]
		],
		"gfVersion": "gf",
		"notes": [
			{
				"sectionNotes": [],
				"lengthInSteps": 16,
				"mustHitSection": false
			},
			{
				"sectionNotes": [],
				"lengthInSteps": 16,
				"mustHitSection": true
			},
			{
				"sectionNotes": [],
				"lengthInSteps": 16,
				"mustHitSection": false
			},
			{
				"sectionNotes": [],
				"lengthInSteps": 16,
				"mustHitSection": false
			},
			{
				"sectionNotes": [],
				"lengthInSteps": 16,
				"mustHitSection": false
			},
			{
				"sectionNotes": [],
				"lengthInSteps": 16,
				"mustHitSection": true
			},
			{
				"sectionNotes": [],
				"lengthInSteps": 16,
				"mustHitSection": false
			},
			{
				"sectionNotes": [],
				"lengthInSteps": 16,
				"mustHitSection": true
			},
			{
				"sectionNotes": [
					[
						12800,
						1,
						500
					],
					[
						13400,
						2,
						300
					],
					[
						13800,
						1,
						500
					]
				],
				"lengthInSteps": 16,
				"mustHitSection": false
			},
			{
				"sectionNotes": [
					[
						14400,
						3,
						600
					]
				],
				"lengthInSteps": 16,
				"mustHitSection": false
			},
			{
				"sectionNotes": [
					[
						16000,
						0,
						500
					],
					[
						16600,
						3,
						300
					],
					[
						17000,
						0,
						500
					]
				],
				"lengthInSteps": 16,
				"mustHitSection": false
			},
			{
				"sectionNotes": [
					[
						17600,
						1,
						500
					],
					[
						18200,
						2,
						500
					],
					[
						18800,
						0,
						0
					],
					[
						19000,
						3,
						0
					]
				],
				"lengthInSteps": 16,
				"mustHitSection": false
			},
			{
				"sectionNotes": [
					[
						19200,
						1,
						500
					],
					[
						19800,
						2,
						300
					],
					[
						20200,
						1,
						500
					],
					[
						19200,
						5,
						500
					]
				],
				"lengthInSteps": 16,
				"mustHitSection": true
			},
			{
				"sectionNotes": [
					[
						20800,
						3,
						600
					]
				],
				"lengthInSteps": 16,
				"mustHitSection": true
			},
			{
				"sectionNotes": [
					[
						22400,
						0,
						500
					],
					[
						23000,
						3,
						300
					],
					[
						23400,
						0,
						500
					]
				],
				"lengthInSteps": 16,
				"mustHitSection": true
			},
			{
				"sectionNotes": [
					[
						24000,
						1,
						500
					],
					[
						24600,
						2,
						500
					],
					[
						25200,
						0,
						0
					],
					[
						25400,
						3,
						0
					]
				],
				"lengthInSteps": 16,
				"mustHitSection": true
			},
			{
				"sectionNotes": [
					[
						25600,
						1,
						0
					],
					[
						25800,
						2,
						0
					],
					[
						25900,
						3,
						0
					],
					[
						26400,
						0,
						100
					],
					[
						26600,
						3,
						100
					],
					[
						26800,
						1,
						100
					],
					[
						26000,
						1,
						100
					],
					[
						26200,
						2,
						100
					],
					[
						25600,
						5,
						900
					]
				],
				"lengthInSteps": 16,
				"mustHitSection": false
			},
			{
				"sectionNotes": [
					[
						27200,
						3,
						100
					],
					[
						27400,
						1,
						100
					],
					[
						27600,
						2,
						100
					],
					[
						27800,
						0,
						100
					],
					[
						28000,
						3,
						100
					],
					[
						28200,
						1,
						100
					],
					[
						28400,
						2,
						100
					],
					[
						28000,
						7,
						700
					]
				],
				"lengthInSteps": 16,
				"mustHitSection": false
			},
			{
				"sectionNotes": [
					[
						30000,
						2,
						100
					],
					[
						28800,
						0,
						100
					],
					[
						29000,
						1,
						100
					],
					[
						29200,
						0,
						100
					],
					[
						29400,
						1,
						100
					],
					[
						29600,
						3,
						100
					],
					[
						28800,
						4,
						900
					]
				],
				"lengthInSteps": 16,
				"mustHitSection": false
			},
			{
				"sectionNotes": [
					[
						31600,
						0,
						100
					],
					[
						30400,
						0,
						100
					],
					[
						30600,
						2,
						100
					],
					[
						30800,
						0,
						100
					],
					[
						31000,
						2,
						100
					],
					[
						31200,
						3,
						100
					],
					[
						31200,
						4,
						700
					]
				],
				"lengthInSteps": 16,
				"mustHitSection": false
			},
			{
				"sectionNotes": [
					[
						32000,
						2,
						300
					],
					[
						33200,
						1,
						300
					],
					[
						32400,
						0,
						300
					],
					[
						32800,
						3,
						300
					],
					[
						32000,
						5,
						700
					]
				],
				"lengthInSteps": 16,
				"mustHitSection": false
			},
			{
				"sectionNotes": [
					[
						33600,
						0,
						100
					],
					[
						33800,
						3,
						100
					],
					[
						34000,
						1,
						100
					],
					[
						34200,
						0,
						100
					],
					[
						34400,
						3,
						100
					],
					[
						34600,
						1,
						100
					],
					[
						34800,
						2,
						100
					],
					[
						35000,
						3,
						100
					],
					[
						34400,
						7,
						700
					]
				],
				"lengthInSteps": 16,
				"mustHitSection": false
			},
			{
				"sectionNotes": [
					[
						36200,
						0,
						100
					],
					[
						36600,
						2,
						100
					],
					[
						35600,
						0,
						0
					],
					[
						35800,
						3,
						0
					],
					[
						35200,
						0,
						0
					],
					[
						35400,
						3,
						0
					],
					[
						35300,
						2,
						0
					],
					[
						35700,
						2,
						0
					],
					[
						36400,
						1,
						100
					],
					[
						36000,
						2,
						100
					],
					[
						35200,
						4,
						1000
					]
				],
				"lengthInSteps": 16,
				"mustHitSection": false
			},
			{
				"sectionNotes": [
					[
						36800,
						1,
						300
					],
					[
						37200,
						3,
						300
					],
					[
						37600,
						0,
						300
					],
					[
						38000,
						3,
						300
					],
					[
						36800,
						6,
						700
					],
					[
						37600,
						4,
						700
					]
				],
				"lengthInSteps": 16,
				"mustHitSection": false
			},
			{
				"sectionNotes": [
					[
						38400,
						1,
						0
					],
					[
						38600,
						2,
						0
					],
					[
						38700,
						3,
						0
					],
					[
						39200,
						0,
						100
					],
					[
						39400,
						3,
						100
					],
					[
						39600,
						1,
						100
					],
					[
						38800,
						1,
						100
					],
					[
						39000,
						2,
						100
					],
					[
						38400,
						5,
						1400
					]
				],
				"lengthInSteps": 16,
				"mustHitSection": true
			},
			{
				"sectionNotes": [
					[
						40000,
						3,
						100
					],
					[
						40200,
						1,
						100
					],
					[
						40400,
						2,
						100
					],
					[
						40600,
						0,
						100
					],
					[
						40800,
						3,
						100
					],
					[
						41000,
						1,
						100
					],
					[
						41200,
						2,
						100
					],
					[
						40800,
						7,
						700
					]
				],
				"lengthInSteps": 16,
				"mustHitSection": true
			},
			{
				"sectionNotes": [
					[
						42800,
						2,
						100
					],
					[
						41600,
						0,
						100
					],
					[
						41800,
						1,
						100
					],
					[
						42000,
						0,
						100
					],
					[
						42200,
						1,
						100
					],
					[
						42400,
						3,
						100
					],
					[
						41600,
						4,
						1500
					]
				],
				"lengthInSteps": 16,
				"mustHitSection": true
			},
			{
				"sectionNotes": [
					[
						44400,
						0,
						100
					],
					[
						43200,
						0,
						100
					],
					[
						43400,
						2,
						100
					],
					[
						43600,
						0,
						100
					],
					[
						43800,
						2,
						100
					],
					[
						44000,
						3,
						100
					],
					[
						44000,
						4,
						800
					]
				],
				"lengthInSteps": 16,
				"mustHitSection": true
			},
			{
				"sectionNotes": [
					[
						44800,
						2,
						300
					],
					[
						46000,
						1,
						300
					],
					[
						45200,
						0,
						300
					],
					[
						45600,
						3,
						300
					],
					[
						44800,
						5,
						1500
					]
				],
				"lengthInSteps": 16,
				"mustHitSection": true
			},
			{
				"sectionNotes": [
					[
						46400,
						0,
						100
					],
					[
						46600,
						3,
						100
					],
					[
						46800,
						1,
						100
					],
					[
						47000,
						0,
						100
					],
					[
						47200,
						3,
						100
					],
					[
						47400,
						1,
						100
					],
					[
						47600,
						2,
						100
					],
					[
						47800,
						3,
						100
					],
					[
						47200,
						7,
						700
					]
				],
				"lengthInSteps": 16,
				"mustHitSection": true
			},
			{
				"sectionNotes": [
					[
						49000,
						0,
						100
					],
					[
						49400,
						2,
						100
					],
					[
						48400,
						0,
						0
					],
					[
						48600,
						3,
						0
					],
					[
						48000,
						0,
						0
					],
					[
						48200,
						3,
						0
					],
					[
						48100,
						2,
						0
					],
					[
						48500,
						2,
						0
					],
					[
						49200,
						1,
						100
					],
					[
						48800,
						2,
						100
					],
					[
						48000,
						4,
						1500
					]
				],
				"lengthInSteps": 16,
				"mustHitSection": true
			},
			{
				"sectionNotes": [
					[
						49600,
						1,
						300
					],
					[
						50000,
						3,
						300
					],
					[
						50400,
						0,
						300
					],
					[
						50800,
						3,
						300
					],
					[
						49600,
						6,
						700
					],
					[
						50400,
						4,
						700
					]
				],
				"lengthInSteps": 16,
				"mustHitSection": true
			},
			{
				"sectionNotes": [
					[
						52000,
						3,
						0
					],
					[
						52100,
						0,
						0
					],
					[
						52400,
						2,
						100
					],
					[
						51400,
						0,
						0
					],
					[
						51300,
						3,
						0
					],
					[
						51600,
						2,
						0
					],
					[
						51700,
						1,
						0
					],
					[
						51800,
						0,
						0
					],
					[
						52200,
						3,
						0
					],
					[
						52300,
						1,
						0
					],
					[
						52600,
						0,
						100
					],
					[
						51200,
						2,
						0
					]
				],
				"lengthInSteps": 16,
				"mustHitSection": false
			},
			{
				"sectionNotes": [
					[
						54000,
						3,
						100
					],
					[
						53400,
						0,
						100
					],
					[
						53200,
						2,
						100
					],
					[
						53600,
						2,
						100
					],
					[
						52800,
						1,
						100
					],
					[
						53000,
						3,
						100
					],
					[
						53800,
						0,
						100
					],
					[
						54200,
						1,
						100
					]
				],
				"lengthInSteps": 16,
				"mustHitSection": false
			},
			{
				"sectionNotes": [
					[
						54400,
						0,
						100
					],
					[
						54600,
						1,
						100
					],
					[
						54800,
						0,
						100
					],
					[
						55000,
						1,
						0
					],
					[
						55100,
						3,
						0
					],
					[
						55200,
						0,
						100
					],
					[
						55400,
						1,
						0
					],
					[
						55500,
						0,
						0
					],
					[
						55800,
						1,
						100
					],
					[
						55600,
						3,
						100
					]
				],
				"lengthInSteps": 16,
				"mustHitSection": false
			},
			{
				"sectionNotes": [
					[
						56000,
						0,
						100
					],
					[
						56400,
						0,
						100
					],
					[
						56200,
						3,
						100
					],
					[
						56600,
						3,
						100
					],
					[
						56800,
						2,
						100
					],
					[
						57200,
						2,
						0
					],
					[
						57000,
						0,
						100
					],
					[
						57300,
						0,
						0
					],
					[
						57400,
						3,
						100
					]
				],
				"lengthInSteps": 16,
				"mustHitSection": false
			},
			{
				"sectionNotes": [
					[
						58400,
						3,
						0
					],
					[
						58500,
						0,
						0
					],
					[
						58800,
						2,
						100
					],
					[
						57800,
						0,
						0
					],
					[
						57700,
						3,
						0
					],
					[
						58000,
						2,
						0
					],
					[
						58100,
						1,
						0
					],
					[
						58200,
						0,
						0
					],
					[
						58600,
						3,
						0
					],
					[
						58700,
						1,
						0
					],
					[
						59000,
						0,
						100
					],
					[
						57600,
						2,
						0
					],
					[
						58800,
						6,
						0
					],
					[
						58200,
						5,
						0
					],
					[
						57600,
						5,
						0
					]
				],
				"lengthInSteps": 16,
				"mustHitSection": true
			},
			{
				"sectionNotes": [
					[
						60400,
						3,
						100
					],
					[
						59800,
						0,
						100
					],
					[
						59600,
						2,
						100
					],
					[
						60000,
						2,
						100
					],
					[
						59200,
						1,
						100
					],
					[
						59400,
						3,
						100
					],
					[
						60200,
						0,
						100
					],
					[
						60600,
						1,
						100
					],
					[
						59800,
						5,
						0
					],
					[
						59200,
						5,
						0
					],
					[
						60400,
						6,
						0
					]
				],
				"lengthInSteps": 16,
				"mustHitSection": true
			},
			{
				"sectionNotes": [
					[
						60800,
						0,
						100
					],
					[
						61000,
						1,
						100
					],
					[
						61200,
						0,
						100
					],
					[
						61400,
						1,
						0
					],
					[
						61500,
						3,
						0
					],
					[
						61600,
						0,
						100
					],
					[
						61800,
						1,
						0
					],
					[
						61900,
						0,
						0
					],
					[
						62200,
						1,
						100
					],
					[
						62000,
						3,
						100
					],
					[
						60800,
						4,
						0
					],
					[
						61400,
						4,
						0
					],
					[
						62000,
						6,
						0
					]
				],
				"lengthInSteps": 16,
				"mustHitSection": true
			},
			{
				"sectionNotes": [
					[
						62400,
						0,
						100
					],
					[
						62800,
						0,
						100
					],
					[
						62600,
						3,
						100
					],
					[
						63000,
						3,
						100
					],
					[
						63200,
						2,
						100
					],
					[
						63600,
						2,
						0
					],
					[
						63400,
						0,
						100
					],
					[
						63700,
						0,
						0
					],
					[
						63800,
						3,
						100
					],
					[
						62400,
						4,
						0
					],
					[
						63000,
						4,
						0
					],
					[
						63600,
						6,
						0
					]
				],
				"lengthInSteps": 16,
				"mustHitSection": true
			},
			{
				"sectionNotes": [
					[
						65200,
						6,
						0
					],
					[
						64600,
						5,
						0
					],
					[
						64000,
						5,
						0
					],
					[
						64800,
						3,
						0
					],
					[
						64900,
						2,
						0
					],
					[
						65000,
						0,
						0
					],
					[
						65100,
						3,
						0
					],
					[
						65400,
						3,
						0
					],
					[
						65200,
						1,
						0
					],
					[
						64000,
						1,
						0
					],
					[
						64500,
						2,
						0
					],
					[
						64600,
						0,
						0
					],
					[
						64100,
						3,
						0
					],
					[
						64200,
						2,
						0
					],
					[
						64300,
						0,
						0
					],
					[
						64400,
						1,
						0
					]
				],
				"lengthInSteps": 16,
				"mustHitSection": false
			},
			{
				"sectionNotes": [
					[
						66200,
						5,
						0
					],
					[
						65600,
						5,
						0
					],
					[
						66800,
						6,
						0
					],
					[
						66200,
						3,
						100
					],
					[
						66400,
						0,
						0
					],
					[
						66500,
						3,
						0
					],
					[
						66600,
						2,
						0
					],
					[
						66700,
						1,
						0
					],
					[
						67000,
						1,
						0
					],
					[
						65600,
						0,
						100
					],
					[
						65800,
						1,
						100
					],
					[
						66000,
						2,
						100
					],
					[
						66800,
						3,
						100
					]
				],
				"lengthInSteps": 16,
				"mustHitSection": false
			},
			{
				"sectionNotes": [
					[
						67200,
						4,
						0
					],
					[
						67800,
						4,
						0
					],
					[
						68400,
						6,
						0
					],
					[
						68300,
						2,
						0
					],
					[
						67300,
						0,
						0
					],
					[
						67600,
						3,
						100
					],
					[
						68000,
						3,
						100
					],
					[
						67200,
						2,
						0
					],
					[
						68400,
						3,
						200
					],
					[
						67800,
						0,
						0
					],
					[
						67900,
						2,
						0
					],
					[
						67400,
						1,
						100
					],
					[
						68200,
						1,
						0
					]
				],
				"lengthInSteps": 16,
				"mustHitSection": false
			},
			{
				"sectionNotes": [
					[
						68800,
						4,
						0
					],
					[
						69400,
						4,
						0
					],
					[
						70000,
						6,
						0
					],
					[
						69800,
						3,
						100
					],
					[
						70000,
						0,
						0
					],
					[
						70100,
						2,
						0
					],
					[
						70200,
						3,
						0
					],
					[
						68900,
						0,
						0
					],
					[
						69400,
						3,
						0
					],
					[
						68800,
						1,
						0
					],
					[
						69200,
						1,
						0
					],
					[
						69000,
						1,
						0
					],
					[
						69100,
						2,
						0
					],
					[
						69300,
						2,
						0
					],
					[
						69500,
						2,
						0
					],
					[
						69600,
						0,
						100
					]
				],
				"lengthInSteps": 16,
				"mustHitSection": false
			},
			{
				"sectionNotes": [
					[
						71200,
						3,
						0
					],
					[
						71300,
						2,
						0
					],
					[
						71400,
						0,
						0
					],
					[
						71500,
						3,
						0
					],
					[
						71800,
						3,
						0
					],
					[
						71600,
						1,
						0
					],
					[
						70400,
						1,
						0
					],
					[
						70900,
						2,
						0
					],
					[
						71000,
						0,
						0
					],
					[
						70500,
						3,
						0
					],
					[
						70600,
						2,
						0
					],
					[
						70700,
						0,
						0
					],
					[
						70800,
						1,
						0
					],
					[
						70400,
						5,
						0
					],
					[
						71000,
						5,
						0
					],
					[
						71600,
						6,
						0
					]
				],
				"lengthInSteps": 16,
				"mustHitSection": true
			},
			{
				"sectionNotes": [
					[
						72600,
						3,
						100
					],
					[
						72800,
						0,
						0
					],
					[
						72900,
						3,
						0
					],
					[
						73000,
						2,
						0
					],
					[
						73100,
						1,
						0
					],
					[
						73400,
						1,
						0
					],
					[
						72000,
						0,
						100
					],
					[
						72200,
						1,
						100
					],
					[
						72400,
						2,
						100
					],
					[
						73200,
						3,
						100
					],
					[
						72000,
						4,
						0
					],
					[
						72600,
						4,
						0
					],
					[
						73200,
						5,
						0
					]
				],
				"lengthInSteps": 16,
				"mustHitSection": true
			},
			{
				"sectionNotes": [
					[
						74700,
						2,
						0
					],
					[
						73700,
						0,
						0
					],
					[
						74000,
						3,
						100
					],
					[
						74400,
						3,
						100
					],
					[
						73600,
						2,
						0
					],
					[
						74800,
						3,
						200
					],
					[
						74200,
						0,
						0
					],
					[
						74300,
						2,
						0
					],
					[
						73800,
						1,
						100
					],
					[
						74600,
						1,
						0
					],
					[
						73600,
						7,
						0
					],
					[
						74200,
						7,
						0
					],
					[
						74800,
						6,
						0
					]
				],
				"lengthInSteps": 16,
				"mustHitSection": true
			},
			{
				"sectionNotes": [
					[
						76200,
						3,
						100
					],
					[
						76400,
						0,
						0
					],
					[
						76500,
						2,
						0
					],
					[
						76600,
						3,
						0
					],
					[
						75300,
						0,
						0
					],
					[
						75800,
						3,
						0
					],
					[
						75200,
						1,
						0
					],
					[
						75600,
						1,
						0
					],
					[
						75400,
						1,
						0
					],
					[
						75500,
						2,
						0
					],
					[
						75700,
						2,
						0
					],
					[
						75900,
						2,
						0
					],
					[
						76000,
						0,
						100
					],
					[
						75200,
						4,
						0
					],
					[
						75800,
						4,
						0
					],
					[
						76400,
						5,
						100
					]
				],
				"lengthInSteps": 16,
				"mustHitSection": true
			},
			{
				"sectionNotes": [
					[
						77600,
						1,
						100
					],
					[
						77800,
						2,
						100
					],
					[
						78000,
						0,
						100
					],
					[
						77000,
						1,
						0
					],
					[
						77100,
						2,
						0
					],
					[
						76800,
						3,
						0
					],
					[
						77200,
						0,
						0
					],
					[
						77400,
						3,
						0
					],
					[
						76800,
						5,
						600
					]
				],
				"lengthInSteps": 16,
				"mustHitSection": false
			},
			{
				"sectionNotes": [
					[
						79200,
						7,
						700
					],
					[
						78400,
						1,
						0
					],
					[
						78600,
						0,
						0
					],
					[
						78800,
						3,
						0
					],
					[
						79000,
						1,
						0
					],
					[
						79200,
						0,
						0
					],
					[
						79266.25,
						3,
						0
					],
					[
						79335,
						2,
						0
					],
					[
						79400,
						1,
						0
					],
					[
						79466.25,
						0,
						0
					],
					[
						79600,
						1,
						100
					],
					[
						79800,
						2,
						100
					]
				],
				"lengthInSteps": 16,
				"mustHitSection": false
			},
			{
				"sectionNotes": [
					[
						80000,
						5,
						800
					],
					[
						80000,
						0,
						100
					],
					[
						80200,
						1,
						100
					],
					[
						80400,
						0,
						100
					],
					[
						80600,
						3,
						100
					],
					[
						80800,
						1,
						100
					],
					[
						81200,
						0,
						0
					]
				],
				"lengthInSteps": 16,
				"mustHitSection": false
			},
			{
				"sectionNotes": [
					[
						81600,
						0,
						100
					],
					[
						81800,
						3,
						100
					],
					[
						82000,
						0,
						100
					],
					[
						82200,
						3,
						100
					],
					[
						82400,
						0,
						100
					],
					[
						82800,
						3,
						100
					],
					[
						82400,
						4,
						700
					]
				],
				"lengthInSteps": 16,
				"mustHitSection": false
			},
			{
				"sectionNotes": [
					[
						84600,
						2,
						100
					],
					[
						84400,
						1,
						100
					],
					[
						83200,
						0,
						0
					],
					[
						83300,
						1,
						0
					],
					[
						83400,
						0,
						0
					],
					[
						83500,
						1,
						0
					],
					[
						83600,
						3,
						0
					],
					[
						83700,
						2,
						0
					],
					[
						83800,
						3,
						0
					],
					[
						83900,
						2,
						0
					],
					[
						84000,
						1,
						0
					],
					[
						84100,
						0,
						0
					],
					[
						84200,
						3,
						0
					],
					[
						84300,
						2,
						0
					],
					[
						83200,
						5,
						900
					]
				],
				"lengthInSteps": 16,
				"mustHitSection": false
			},
			{
				"sectionNotes": [
					[
						85600,
						5,
						700
					],
					[
						86200,
						3,
						100
					],
					[
						85600,
						5,
						700
					],
					[
						84800,
						0,
						100
					],
					[
						85000,
						3,
						100
					],
					[
						85200,
						2,
						100
					],
					[
						85400,
						0,
						100
					],
					[
						85600,
						3,
						100
					],
					[
						85800,
						2,
						100
					],
					[
						86000,
						1,
						100
					]
				],
				"lengthInSteps": 16,
				"mustHitSection": false
			},
			{
				"sectionNotes": [
					[
						87400,
						0,
						100
					],
					[
						87800,
						2,
						100
					],
					[
						86800,
						0,
						0
					],
					[
						87000,
						3,
						0
					],
					[
						86400,
						0,
						0
					],
					[
						86600,
						3,
						0
					],
					[
						86500,
						2,
						0
					],
					[
						86900,
						2,
						0
					],
					[
						87600,
						1,
						100
					],
					[
						87200,
						2,
						100
					],
					[
						86400,
						7,
						700
					]
				],
				"lengthInSteps": 16,
				"mustHitSection": false
			},
			{
				"sectionNotes": [
					[
						88000,
						6,
						800
					],
					[
						88000,
						1,
						300
					],
					[
						88400,
						3,
						300
					],
					[
						88800,
						1,
						700
					]
				],
				"lengthInSteps": 16,
				"mustHitSection": false
			},
			{
				"sectionNotes": [
					[
						90400,
						1,
						100
					],
					[
						90600,
						2,
						100
					],
					[
						90800,
						0,
						100
					],
					[
						89800,
						1,
						0
					],
					[
						89900,
						2,
						0
					],
					[
						89600,
						3,
						0
					],
					[
						90000,
						0,
						0
					],
					[
						90200,
						3,
						0
					],
					[
						89600,
						7,
						1500
					]
				],
				"lengthInSteps": 16,
				"mustHitSection": true
			},
			{
				"sectionNotes": [
					[
						91200,
						1,
						0
					],
					[
						91400,
						0,
						0
					],
					[
						91600,
						3,
						0
					],
					[
						91800,
						1,
						0
					],
					[
						92000,
						0,
						0
					],
					[
						92066.25,
						3,
						0
					],
					[
						92135,
						2,
						0
					],
					[
						92200,
						1,
						0
					],
					[
						92266.25,
						0,
						0
					],
					[
						92400,
						1,
						100
					],
					[
						92600,
						2,
						100
					],
					[
						92000,
						4,
						700
					]
				],
				"lengthInSteps": 16,
				"mustHitSection": true
			},
			{
				"sectionNotes": [
					[
						92800,
						0,
						100
					],
					[
						93000,
						1,
						100
					],
					[
						93200,
						0,
						100
					],
					[
						93400,
						3,
						100
					],
					[
						93600,
						1,
						100
					],
					[
						94000,
						0,
						0
					],
					[
						92800,
						6,
						1500
					]
				],
				"lengthInSteps": 16,
				"mustHitSection": true
			},
			{
				"sectionNotes": [
					[
						94400,
						0,
						100
					],
					[
						94600,
						3,
						100
					],
					[
						94800,
						0,
						100
					],
					[
						95000,
						3,
						100
					],
					[
						95200,
						0,
						100
					],
					[
						95600,
						3,
						100
					],
					[
						95200,
						5,
						700
					]
				],
				"lengthInSteps": 16,
				"mustHitSection": true
			},
			{
				"sectionNotes": [
					[
						97400,
						2,
						100
					],
					[
						97200,
						1,
						100
					],
					[
						96000,
						0,
						0
					],
					[
						96100,
						1,
						0
					],
					[
						96200,
						0,
						0
					],
					[
						96300,
						1,
						0
					],
					[
						96400,
						3,
						0
					],
					[
						96500,
						2,
						0
					],
					[
						96600,
						3,
						0
					],
					[
						96700,
						2,
						0
					],
					[
						96800,
						1,
						0
					],
					[
						96900,
						0,
						0
					],
					[
						97000,
						3,
						0
					],
					[
						97100,
						2,
						0
					],
					[
						96000,
						7,
						1500
					]
				],
				"lengthInSteps": 16,
				"mustHitSection": true
			},
			{
				"sectionNotes": [
					[
						99000,
						3,
						100
					],
					[
						97700,
						3,
						0
					],
					[
						97800,
						2,
						0
					],
					[
						98000,
						1,
						0
					],
					[
						98200,
						2,
						0
					],
					[
						97600,
						0,
						0
					],
					[
						98100,
						3,
						0
					],
					[
						98400,
						0,
						0
					],
					[
						98500,
						1,
						0
					],
					[
						98600,
						3,
						0
					],
					[
						98800,
						2,
						100
					],
					[
						98400,
						5,
						700
					]
				],
				"lengthInSteps": 16,
				"mustHitSection": true
			},
			{
				"sectionNotes": [
					[
						99200,
						7,
						1500
					],
					[
						100200,
						0,
						100
					],
					[
						100600,
						2,
						100
					],
					[
						99600,
						0,
						0
					],
					[
						99800,
						3,
						0
					],
					[
						99200,
						0,
						0
					],
					[
						99400,
						3,
						0
					],
					[
						99300,
						2,
						0
					],
					[
						99700,
						2,
						0
					],
					[
						100400,
						1,
						100
					],
					[
						100000,
						2,
						100
					]
				],
				"lengthInSteps": 16,
				"mustHitSection": true
			},
			{
				"sectionNotes": [
					[
						100800,
						1,
						300
					],
					[
						101200,
						3,
						300
					],
					[
						101600,
						0,
						0
					],
					[
						101800,
						0,
						0
					],
					[
						102200,
						1,
						0
					],
					[
						100800,
						4,
						800
					],
					[
						101800,
						5,
						0
					],
					[
						102000,
						5,
						0
					],
					[
						102200,
						5,
						0
					]
				],
				"lengthInSteps": 16,
				"mustHitSection": true
			},
			{
				"sectionNotes": [
					[
						102400,
						3,
						700
					],
					[
						102400,
						6,
						727.272727272727
					]
				],
				"lengthInSteps": 16,
				"bpm": 165,
				"mustHitSection": true,
				"changeBPM": true
			},
			{
				"lengthInSteps": 16,
				"typeOfSection": 0,
				"sectionNotes": [],
				"altAnim": false,
				"gfSection": false,
				"bpm": 180,
				"changeBPM": false,
				"mustHitSection": false
			},
			{
				"lengthInSteps": 16,
				"typeOfSection": 0,
				"sectionNotes": [],
				"altAnim": false,
				"gfSection": false,
				"bpm": 150,
				"changeBPM": false,
				"mustHitSection": false
			},
			{
				"lengthInSteps": 16,
				"typeOfSection": 0,
				"sectionNotes": [
					[
						107490.909090909,
						2,
						272.727272727273
					],
					[
						107854.545454545,
						0,
						272.727272727273
					]
				],
				"altAnim": false,
				"gfSection": false,
				"bpm": 150,
				"changeBPM": false,
				"mustHitSection": false
			},
			{
				"lengthInSteps": 16,
				"typeOfSection": 0,
				"sectionNotes": [
					[
						108218.181818182,
						1,
						0
					],
					[
						108400,
						3,
						0
					],
					[
						108490.909090909,
						0,
						0
					],
					[
						108581.818181818,
						1,
						90.9090909090909
					],
					[
						108763.636363636,
						3,
						0
					],
					[
						108854.545454545,
						2,
						0
					],
					[
						108945.454545454,
						1,
						0
					],
					[
						109036.363636363,
						0,
						0
					],
					[
						109218.181818182,
						0,
						0
					],
					[
						109490.909090909,
						3,
						90.9090909090909
					],
					[
						109309.090909091,
						3,
						0
					],
					[
						109400,
						1,
						0
					],
					[
						109127.272727273,
						2,
						0
					]
				],
				"altAnim": false,
				"gfSection": false,
				"bpm": 150,
				"changeBPM": false,
				"mustHitSection": false
			},
			{
				"lengthInSteps": 16,
				"typeOfSection": 0,
				"sectionNotes": [
					[
						109854.545454545,
						3,
						0
					],
					[
						109945.454545454,
						2,
						0
					],
					[
						110036.363636363,
						3,
						0
					],
					[
						110309.090909091,
						3,
						0
					],
					[
						110400,
						1,
						90.9090909090909
					],
					[
						110581.818181818,
						0,
						90.9090909090909
					],
					[
						110763.636363636,
						3,
						90.9090909090909
					],
					[
						110945.454545454,
						1,
						90.9090909090909
					],
					[
						109672.727272727,
						1,
						90.9090909090909
					],
					[
						110127.272727273,
						0,
						0
					],
					[
						110218.181818182,
						1,
						0
					]
				],
				"altAnim": false,
				"gfSection": false,
				"bpm": 150,
				"changeBPM": false,
				"mustHitSection": false
			},
			{
				"lengthInSteps": 16,
				"typeOfSection": 0,
				"sectionNotes": [
					[
						111127.272727273,
						0,
						90.9090909090909
					],
					[
						111309.090909091,
						2,
						0
					],
					[
						111400,
						1,
						0
					],
					[
						111490.909090909,
						3,
						90.9090909090909
					],
					[
						111672.727272727,
						1,
						90.9090909090909
					],
					[
						111854.545454545,
						3,
						0
					],
					[
						111945.454545454,
						0,
						0
					],
					[
						112036.363636363,
						2,
						90.9090909090909
					],
					[
						112218.181818182,
						0,
						90.9090909090909
					],
					[
						112400,
						3,
						90.9090909090909
					]
				],
				"altAnim": false,
				"gfSection": false,
				"bpm": 150,
				"changeBPM": false,
				"mustHitSection": false
			},
			{
				"sectionNotes": [
					[
						113309.090909091,
						6,
						272.727272727273
					],
					[
						113672.727272727,
						4,
						272.727272727273
					],
					[
						113854.545454545,
						2,
						90.9090909090909
					],
					[
						113672.727272727,
						0,
						90.9090909090909
					],
					[
						113400,
						0,
						0
					],
					[
						112581.818181818,
						0,
						0
					],
					[
						112672.727272727,
						3,
						0
					],
					[
						112763.636363636,
						2,
						0
					],
					[
						112854.545454545,
						1,
						0
					],
					[
						112945.454545454,
						3,
						90.9090909090909
					],
					[
						113127.272727273,
						1,
						0
					],
					[
						113218.181818182,
						1,
						0
					],
					[
						113309.090909091,
						3,
						0
					],
					[
						113490.909090909,
						2,
						0
					],
					[
						113581.818181818,
						1,
						0
					]
				],
				"typeOfSection": 0,
				"lengthInSteps": 16,
				"gfSection": false,
				"altAnim": false,
				"mustHitSection": false,
				"changeBPM": false,
				"bpm": 150
			},
			{
				"sectionNotes": [
					[
						114036.363636364,
						5,
						0
					],
					[
						114218.181818182,
						7,
						0
					],
					[
						114309.090909091,
						4,
						0
					],
					[
						114400,
						5,
						90.9090909090909
					],
					[
						114581.818181818,
						7,
						0
					],
					[
						114672.727272727,
						6,
						0
					],
					[
						114763.636363636,
						5,
						0
					],
					[
						114854.545454545,
						4,
						0
					],
					[
						115036.363636364,
						4,
						0
					],
					[
						115309.090909091,
						7,
						90.9090909090909
					],
					[
						115127.272727273,
						7,
						0
					],
					[
						115218.181818182,
						5,
						0
					],
					[
						114945.454545455,
						6,
						0
					],
					[
						114036.363636364,
						3,
						272.727272727273
					],
					[
						114400,
						0,
						272.727272727273
					],
					[
						114763.636363636,
						2,
						636.363636363636
					]
				],
				"typeOfSection": 0,
				"lengthInSteps": 16,
				"gfSection": false,
				"altAnim": false,
				"mustHitSection": false,
				"changeBPM": false,
				"bpm": 150
			},
			{
				"sectionNotes": [
					[
						115672.727272727,
						7,
						0
					],
					[
						115763.636363636,
						6,
						0
					],
					[
						115854.545454545,
						7,
						0
					],
					[
						116127.272727273,
						7,
						0
					],
					[
						116218.181818182,
						5,
						90.9090909090909
					],
					[
						116400,
						4,
						90.9090909090909
					],
					[
						116581.818181818,
						7,
						90.9090909090909
					],
					[
						116763.636363636,
						5,
						90.9090909090909
					],
					[
						115490.909090909,
						5,
						90.9090909090909
					],
					[
						115945.454545455,
						4,
						0
					],
					[
						116036.363636364,
						5,
						0
					],
					[
						116763.636363636,
						1,
						90.9090909090909
					]
				],
				"typeOfSection": 0,
				"lengthInSteps": 16,
				"gfSection": false,
				"altAnim": false,
				"mustHitSection": false,
				"changeBPM": false,
				"bpm": 150
			},
			{
				"sectionNotes": [
					[
						116945.454545455,
						4,
						90.9090909090909
					],
					[
						117127.272727273,
						6,
						0
					],
					[
						117218.181818182,
						5,
						0
					],
					[
						117309.090909091,
						7,
						90.9090909090909
					],
					[
						117490.909090909,
						5,
						90.9090909090909
					],
					[
						117672.727272727,
						7,
						0
					],
					[
						117763.636363636,
						4,
						0
					],
					[
						117854.545454545,
						6,
						90.9090909090909
					],
					[
						118036.363636364,
						4,
						90.9090909090909
					],
					[
						118218.181818182,
						7,
						90.9090909090909
					],
					[
						116945.454545455,
						2,
						272.727272727273
					],
					[
						117309.090909091,
						3,
						181.818181818182
					],
					[
						117581.818181818,
						0,
						90.9090909090909
					],
					[
						117763.636363636,
						1,
						0
					],
					[
						117854.545454545,
						3,
						0
					],
					[
						118036.363636364,
						1,
						272.727272727273
					]
				],
				"typeOfSection": 0,
				"lengthInSteps": 16,
				"gfSection": false,
				"altAnim": false,
				"mustHitSection": false,
				"changeBPM": false,
				"bpm": 150
			},
			{
				"sectionNotes": [
					[
						119672.727272727,
						6,
						90.9090909090909
					],
					[
						119490.909090909,
						4,
						90.9090909090909
					],
					[
						119218.181818182,
						4,
						0
					],
					[
						118400,
						4,
						0
					],
					[
						118490.909090909,
						7,
						0
					],
					[
						118581.818181818,
						6,
						0
					],
					[
						118672.727272727,
						5,
						0
					],
					[
						118763.636363636,
						7,
						90.9090909090909
					],
					[
						118945.454545455,
						5,
						0
					],
					[
						119036.363636364,
						5,
						0
					],
					[
						119127.272727273,
						7,
						0
					],
					[
						119309.090909091,
						6,
						0
					],
					[
						119400,
						5,
						0
					],
					[
						118400,
						3,
						636.363636363636
					],
					[
						119127.272727273,
						2,
						636.363636363636
					]
				],
				"typeOfSection": 0,
				"lengthInSteps": 16,
				"gfSection": false,
				"altAnim": false,
				"mustHitSection": false,
				"changeBPM": false,
				"bpm": 150
			},
			{
				"sectionNotes": [
					[
						119854.545454545,
						7,
						727.272727272727
					],
					[
						119854.545454545,
						1,
						90.9090909090909
					],
					[
						120036.363636363,
						3,
						90.9090909090909
					],
					[
						120218.181818182,
						0,
						90.9090909090909
					],
					[
						120400,
						3,
						0
					],
					[
						120490.909090909,
						2,
						0
					],
					[
						120581.818181818,
						3,
						0
					],
					[
						120672.727272727,
						0,
						0
					],
					[
						120763.636363636,
						2,
						0
					],
					[
						120854.545454545,
						3,
						0
					],
					[
						120945.454545454,
						1,
						90.9090909090909
					],
					[
						121127.272727273,
						3,
						90.9090909090909
					]
				],
				"typeOfSection": 0,
				"lengthInSteps": 16,
				"gfSection": false,
				"altAnim": false,
				"mustHitSection": false,
				"changeBPM": false,
				"bpm": 150
			},
			{
				"sectionNotes": [
					[
						122036.363636364,
						7,
						636.363636363636
					],
					[
						121309.090909091,
						0,
						90.9090909090909
					],
					[
						121490.909090909,
						3,
						90.9090909090909
					],
					[
						121672.727272727,
						2,
						90.9090909090909
					],
					[
						121854.545454545,
						0,
						90.9090909090909
					],
					[
						122036.363636363,
						3,
						0
					],
					[
						122127.272727273,
						3,
						0
					],
					[
						122218.181818182,
						1,
						90.9090909090909
					],
					[
						122400,
						0,
						90.9090909090909
					],
					[
						122581.818181818,
						1,
						90.9090909090909
					]
				],
				"typeOfSection": 0,
				"lengthInSteps": 16,
				"gfSection": false,
				"altAnim": false,
				"mustHitSection": false,
				"changeBPM": false,
				"bpm": 150
			},
			{
				"sectionNotes": [
					[
						122763.636363636,
						5,
						272.727272727273
					],
					[
						123127.272727273,
						7,
						272.727272727273
					],
					[
						123490.909090909,
						4,
						272.727272727273
					],
					[
						123854.545454545,
						7,
						272.727272727273
					],
					[
						123127.272727273,
						0,
						90.9090909090909
					],
					[
						122763.636363636,
						3,
						272.727272727273
					],
					[
						123309.090909091,
						1,
						272.727272727273
					],
					[
						123672.727272727,
						2,
						90.9090909090909
					],
					[
						123854.545454545,
						3,
						90.9090909090909
					],
					[
						124036.363636363,
						1,
						90.9090909090909
					]
				],
				"typeOfSection": 0,
				"lengthInSteps": 16,
				"gfSection": false,
				"altAnim": false,
				"mustHitSection": false,
				"changeBPM": false,
				"bpm": 150
			},
			{
				"sectionNotes": [
					[
						124400,
						5,
						0
					],
					[
						124945.454545455,
						7,
						90.9090909090909
					],
					[
						125127.272727273,
						5,
						90.9090909090909
					],
					[
						125309.090909091,
						4,
						90.9090909090909
					],
					[
						125490.909090909,
						6,
						90.9090909090909
					],
					[
						124218.181818182,
						6,
						90.9090909090909
					],
					[
						124581.818181818,
						7,
						90.9090909090909
					],
					[
						124763.636363636,
						4,
						90.9090909090909
					],
					[
						124218.181818182,
						0,
						0
					],
					[
						124309.090909091,
						1,
						0
					],
					[
						124400,
						0,
						0
					],
					[
						124490.909090909,
						1,
						0
					],
					[
						124581.818181818,
						2,
						0
					],
					[
						124672.727272727,
						1,
						0
					],
					[
						124763.636363636,
						2,
						0
					],
					[
						125127.272727273,
						0,
						90.9090909090909
					],
					[
						125309.090909091,
						1,
						90.9090909090909
					],
					[
						125490.909090909,
						3,
						90.9090909090909
					],
					[
						124945.454545454,
						3,
						90.9090909090909
					],
					[
						124854.545454545,
						0,
						0
					]
				],
				"typeOfSection": 0,
				"lengthInSteps": 16,
				"gfSection": false,
				"altAnim": false,
				"mustHitSection": false,
				"changeBPM": false,
				"bpm": 150
			},
			{
				"lengthInSteps": 16,
				"typeOfSection": 0,
				"sectionNotes": [
					[
						125672.727272727,
						5,
						90.9090909090909
					],
					[
						125854.545454545,
						7,
						90.9090909090909
					],
					[
						126036.363636364,
						4,
						90.9090909090909
					],
					[
						126218.181818182,
						7,
						0
					],
					[
						126309.090909091,
						6,
						0
					],
					[
						126400,
						7,
						0
					],
					[
						126490.909090909,
						4,
						0
					],
					[
						126581.818181818,
						6,
						0
					],
					[
						126672.727272727,
						7,
						0
					],
					[
						126763.636363636,
						5,
						90.9090909090909
					],
					[
						126945.454545455,
						7,
						90.9090909090909
					],
					[
						125672.727272727,
						0,
						727.272727272727
					]
				],
				"altAnim": false,
				"gfSection": false,
				"bpm": 150,
				"changeBPM": false,
				"mustHitSection": false
			},
			{
				"sectionNotes": [
					[
						127127.272727273,
						4,
						90.9090909090909
					],
					[
						127309.090909091,
						7,
						90.9090909090909
					],
					[
						127490.909090909,
						6,
						90.9090909090909
					],
					[
						127672.727272727,
						4,
						90.9090909090909
					],
					[
						127854.545454545,
						7,
						0
					],
					[
						127945.454545455,
						7,
						0
					],
					[
						128036.363636364,
						5,
						90.9090909090909
					],
					[
						128218.181818182,
						4,
						90.9090909090909
					],
					[
						128400,
						5,
						90.9090909090909
					],
					[
						127854.545454545,
						3,
						636.363636363636
					]
				],
				"typeOfSection": 0,
				"lengthInSteps": 16,
				"gfSection": false,
				"altAnim": false,
				"mustHitSection": false,
				"changeBPM": false,
				"bpm": 150
			},
			{
				"sectionNotes": [
					[
						128945.454545455,
						4,
						90.9090909090909
					],
					[
						128581.818181818,
						7,
						272.727272727273
					],
					[
						129127.272727273,
						5,
						272.727272727273
					],
					[
						129490.909090909,
						6,
						90.9090909090909
					],
					[
						129672.727272727,
						7,
						90.9090909090909
					],
					[
						129854.545454545,
						5,
						90.9090909090909
					],
					[
						128581.818181818,
						1,
						272.727272727273
					],
					[
						128945.454545455,
						0,
						272.727272727273
					],
					[
						129309.090909091,
						3,
						363.636363636364
					],
					[
						129763.636363636,
						0,
						181.818181818182
					]
				],
				"typeOfSection": 0,
				"lengthInSteps": 16,
				"gfSection": false,
				"altAnim": false,
				"mustHitSection": false,
				"changeBPM": false,
				"bpm": 150
			},
			{
				"sectionNotes": [
					[
						130036.363636364,
						4,
						0
					],
					[
						130127.272727273,
						5,
						0
					],
					[
						130218.181818182,
						4,
						0
					],
					[
						130309.090909091,
						5,
						0
					],
					[
						130400,
						6,
						0
					],
					[
						130490.909090909,
						5,
						0
					],
					[
						130581.818181818,
						6,
						0
					],
					[
						130945.454545455,
						4,
						90.9090909090909
					],
					[
						131127.272727273,
						5,
						90.9090909090909
					],
					[
						131309.090909091,
						7,
						90.9090909090909
					],
					[
						130763.636363636,
						7,
						90.9090909090909
					],
					[
						130672.727272727,
						4,
						0
					],
					[
						130218.181818182,
						1,
						0
					],
					[
						130763.636363637,
						3,
						90.9090909090909
					],
					[
						130945.454545455,
						1,
						90.9090909090909
					],
					[
						131127.272727273,
						0,
						90.9090909090909
					],
					[
						131309.090909091,
						2,
						90.9090909090909
					],
					[
						130036.363636364,
						2,
						90.9090909090909
					],
					[
						130400,
						3,
						90.9090909090909
					],
					[
						130581.818181818,
						0,
						90.9090909090909
					]
				],
				"typeOfSection": 0,
				"lengthInSteps": 16,
				"gfSection": false,
				"altAnim": false,
				"mustHitSection": false,
				"changeBPM": false,
				"bpm": 150
			},
			{
				"sectionNotes": [
					[
						131490.909090909,
						6,
						636.363636363636
					],
					[
						132218.181818182,
						7,
						636.363636363636
					],
					[
						131490.909090909,
						1,
						636.363636363636
					],
					[
						132763.636363636,
						3,
						0
					],
					[
						132854.545454545,
						0,
						0
					]
				],
				"typeOfSection": 0,
				"lengthInSteps": 16,
				"gfSection": false,
				"altAnim": false,
				"mustHitSection": false,
				"changeBPM": false,
				"bpm": 150
			},
			{
				"sectionNotes": [
					[
						132945.454545455,
						4,
						0
					],
					[
						133534.090909091,
						4,
						0
					],
					[
						133895.454545455,
						6,
						0
					],
					[
						134077.272727273,
						5,
						0
					],
					[
						134256.818181818,
						7,
						0
					],
					[
						133350,
						7,
						0
					],
					[
						132945.454545455,
						1,
						90.9090909090909
					],
					[
						133127.272727273,
						3,
						90.9090909090909
					],
					[
						133309.090909091,
						0,
						90.9090909090909
					],
					[
						133490.909090909,
						2,
						90.9090909090909
					],
					[
						133672.727272727,
						3,
						181.818181818182
					],
					[
						133990.909090909,
						0,
						272.727272727273
					]
				],
				"typeOfSection": 0,
				"lengthInSteps": 16,
				"gfSection": false,
				"altAnim": false,
				"mustHitSection": false,
				"changeBPM": false,
				"bpm": 150
			},
			{
				"sectionNotes": [
					[
						134400,
						5,
						272.727272727273
					],
					[
						134763.636363636,
						7,
						727.272727272727
					],
					[
						134400,
						3,
						272.727272727273
					],
					[
						134763.636363636,
						0,
						90.9090909090909
					],
					[
						134990.909090909,
						1,
						272.727272727273
					],
					[
						135354.545454545,
						0,
						90.9090909090909
					],
					[
						135536.363636364,
						3,
						90.9090909090909
					],
					[
						135718.181818182,
						1,
						90.9090909090909
					]
				],
				"typeOfSection": 0,
				"lengthInSteps": 16,
				"gfSection": false,
				"altAnim": false,
				"mustHitSection": false,
				"changeBPM": false,
				"bpm": 150
			},
			{
				"sectionNotes": [
					[
						135900,
						6,
						272.727272727273
					],
					[
						136263.636363636,
						4,
						636.363636363636
					],
					[
						135900,
						2,
						272.727272727273
					],
					[
						136400,
						0,
						0
					],
					[
						136490.909090909,
						3,
						0
					],
					[
						136581.818181818,
						2,
						90.9090909090909
					],
					[
						136763.636363636,
						0,
						90.9090909090909
					],
					[
						136945.454545455,
						1,
						272.727272727273
					]
				],
				"typeOfSection": 0,
				"lengthInSteps": 16,
				"gfSection": false,
				"altAnim": false,
				"mustHitSection": false,
				"changeBPM": false,
				"bpm": 150
			},
			{
				"sectionNotes": [
					[
						137354.545454545,
						5,
						636.363636363636
					],
					[
						138581.818181818,
						7,
						0
					],
					[
						138672.727272727,
						4,
						0
					],
					[
						137309.090909091,
						3,
						181.818181818182
					],
					[
						137581.818181818,
						1,
						727.272727272727
					]
				],
				"typeOfSection": 0,
				"lengthInSteps": 16,
				"gfSection": false,
				"altAnim": false,
				"mustHitSection": false,
				"changeBPM": false,
				"bpm": 150
			},
			{
				"sectionNotes": [
					[
						139854.545454545,
						7,
						272.727272727273
					],
					[
						138763.636363636,
						5,
						90.9090909090909
					],
					[
						138945.454545455,
						6,
						90.9090909090909
					],
					[
						139127.272727273,
						5,
						90.9090909090909
					],
					[
						139309.090909091,
						7,
						90.9090909090909
					],
					[
						139490.909090909,
						4,
						272.727272727273
					],
					[
						138763.636363636,
						1,
						636.363636363636
					],
					[
						139490.909090909,
						3,
						636.363636363636
					]
				],
				"typeOfSection": 0,
				"lengthInSteps": 16,
				"gfSection": false,
				"altAnim": false,
				"mustHitSection": false,
				"changeBPM": false,
				"bpm": 150
			},
			{
				"sectionNotes": [
					[
						140218.181818182,
						6,
						272.727272727273
					],
					[
						140763.636363636,
						6,
						272.727272727273
					],
					[
						140581.818181818,
						4,
						90.9090909090909
					],
					[
						141127.272727273,
						4,
						90.9090909090909
					],
					[
						141309.090909091,
						7,
						90.9090909090909
					],
					[
						141490.909090909,
						5,
						90.9090909090909
					],
					[
						140218.181818182,
						2,
						0
					],
					[
						140581.818181818,
						0,
						0
					],
					[
						140763.636363636,
						2,
						0
					],
					[
						141127.272727273,
						0,
						0
					],
					[
						141309.090909091,
						3,
						0
					],
					[
						141490.909090909,
						1,
						0
					]
				],
				"typeOfSection": 0,
				"lengthInSteps": 16,
				"gfSection": false,
				"altAnim": false,
				"mustHitSection": false,
				"changeBPM": false,
				"bpm": 150
			},
			{
				"sectionNotes": [
					[
						141672.727272727,
						4,
						272.727272727273
					],
					[
						142218.181818182,
						7,
						0
					],
					[
						142309.090909091,
						6,
						0
					],
					[
						142400,
						4,
						90.9090909090909
					],
					[
						142581.818181818,
						7,
						90.9090909090909
					],
					[
						142763.636363636,
						6,
						272.727272727273
					],
					[
						141672.727272727,
						0,
						272.727272727273
					],
					[
						142036.363636364,
						3,
						636.363636363636
					]
				],
				"typeOfSection": 0,
				"lengthInSteps": 16,
				"gfSection": false,
				"altAnim": false,
				"mustHitSection": false,
				"changeBPM": false,
				"bpm": 150
			},
			{
				"sectionNotes": [
					[
						143127.272727273,
						4,
						272.727272727273
					],
					[
						143490.909090909,
						7,
						272.727272727273
					],
					[
						143854.545454545,
						5,
						181.818181818182
					],
					[
						144218.181818182,
						7,
						0
					],
					[
						144400,
						4,
						0
					],
					[
						143127.272727273,
						0,
						272.727272727273
					],
					[
						143490.909090909,
						3,
						636.363636363636
					]
				],
				"typeOfSection": 0,
				"lengthInSteps": 16,
				"gfSection": false,
				"altAnim": false,
				"mustHitSection": false,
				"changeBPM": false,
				"bpm": 150
			},
			{
				"sectionNotes": [
					[
						144581.818181818,
						6,
						272.727272727273
					],
					[
						144945.454545454,
						5,
						272.727272727273
					],
					[
						145309.090909091,
						7,
						272.727272727273
					],
					[
						145672.727272727,
						5,
						0
					],
					[
						145854.545454545,
						5,
						0
					],
					[
						144581.818181818,
						2,
						636.363636363636
					],
					[
						145309.090909091,
						1,
						636.363636363636
					]
				],
				"typeOfSection": 0,
				"lengthInSteps": 16,
				"gfSection": false,
				"altAnim": false,
				"mustHitSection": false,
				"changeBPM": false,
				"bpm": 150
			},
			{
				"sectionNotes": [
					[
						146036.363636364,
						7,
						0
					],
					[
						146127.272727273,
						6,
						0
					],
					[
						146763.636363636,
						5,
						90.9090909090909
					],
					[
						146945.454545454,
						4,
						90.9090909090909
					],
					[
						147127.272727273,
						7,
						90.9090909090909
					],
					[
						147309.090909091,
						5,
						90.9090909090909
					],
					[
						146218.181818182,
						4,
						0
					],
					[
						146309.090909091,
						5,
						0
					],
					[
						146400,
						7,
						90.9090909090909
					],
					[
						146581.818181818,
						6,
						90.9090909090909
					],
					[
						146036.363636364,
						3,
						0
					],
					[
						146127.272727273,
						2,
						0
					],
					[
						146763.636363636,
						1,
						90.9090909090909
					],
					[
						146945.454545454,
						0,
						90.9090909090909
					],
					[
						147127.272727273,
						3,
						90.9090909090909
					],
					[
						147309.090909091,
						1,
						90.9090909090909
					],
					[
						146218.181818182,
						0,
						0
					],
					[
						146309.090909091,
						1,
						0
					],
					[
						146400,
						3,
						90.9090909090909
					],
					[
						146581.818181818,
						2,
						90.9090909090909
					]
				],
				"typeOfSection": 0,
				"lengthInSteps": 16,
				"gfSection": false,
				"altAnim": false,
				"mustHitSection": false,
				"changeBPM": false,
				"bpm": 150
			},
			{
				"sectionNotes": [
					[
						147490.909090909,
						6,
						90.9090909090909
					],
					[
						147672.727272727,
						4,
						90.9090909090909
					],
					[
						147763.636363636,
						7,
						0
					],
					[
						147854.545454545,
						5,
						90.9090909090909
					],
					[
						148036.363636364,
						6,
						90.9090909090909
					],
					[
						148218.181818182,
						4,
						90.9090909090909
					],
					[
						148400,
						7,
						90.9090909090909
					],
					[
						148581.818181818,
						6,
						90.9090909090909
					],
					[
						148763.636363636,
						5,
						90.9090909090909
					],
					[
						147490.909090909,
						2,
						90.9090909090909
					],
					[
						147763.636363636,
						3,
						0
					],
					[
						148036.363636364,
						2,
						90.9090909090909
					],
					[
						148218.181818182,
						0,
						90.9090909090909
					],
					[
						148400,
						3,
						90.9090909090909
					],
					[
						148581.818181818,
						2,
						90.9090909090909
					],
					[
						148763.636363636,
						1,
						90.9090909090909
					],
					[
						147672.727272727,
						0,
						0
					],
					[
						147854.545454545,
						1,
						0
					],
					[
						147945.454545454,
						1,
						0
					]
				],
				"typeOfSection": 0,
				"lengthInSteps": 16,
				"gfSection": false,
				"altAnim": false,
				"mustHitSection": false,
				"changeBPM": false,
				"bpm": 150
			},
			{
				"sectionNotes": [
					[
						148945.454545454,
						7,
						272.727272727273
					],
					[
						149309.090909091,
						5,
						272.727272727273
					],
					[
						149672.727272727,
						7,
						272.727272727273
					],
					[
						150036.363636364,
						4,
						272.727272727273
					],
					[
						149672.727272727,
						3,
						272.727272727273
					],
					[
						150036.363636364,
						0,
						272.727272727273
					],
					[
						148945.454545454,
						3,
						90.9090909090909
					],
					[
						149127.272727273,
						2,
						90.9090909090909
					],
					[
						149309.090909091,
						0,
						90.9090909090909
					],
					[
						149490.909090909,
						1,
						90.9090909090909
					]
				],
				"typeOfSection": 0,
				"lengthInSteps": 16,
				"gfSection": false,
				"altAnim": false,
				"mustHitSection": false,
				"changeBPM": false,
				"bpm": 150
			},
			{
				"sectionNotes": [
					[
						150400,
						5,
						0
					],
					[
						150581.818181818,
						5,
						0
					],
					[
						150763.636363636,
						7,
						272.727272727273
					],
					[
						151127.272727273,
						5,
						272.727272727273
					],
					[
						151490.909090909,
						4,
						272.727272727273
					],
					[
						150400,
						3,
						636.363636363636
					],
					[
						151127.272727273,
						1,
						636.363636363636
					]
				],
				"typeOfSection": 0,
				"lengthInSteps": 16,
				"gfSection": false,
				"altAnim": false,
				"mustHitSection": false,
				"changeBPM": false,
				"bpm": 150
			},
			{
				"sectionNotes": [
					[
						151854.545454545,
						7,
						272.727272727273
					],
					[
						152218.181818182,
						4,
						272.727272727273
					],
					[
						152581.818181818,
						5,
						0
					],
					[
						152763.636363636,
						7,
						0
					],
					[
						152945.454545454,
						5,
						90.9090909090909
					],
					[
						153127.272727273,
						6,
						90.9090909090909
					],
					[
						151854.545454545,
						0,
						636.363636363636
					],
					[
						152581.818181818,
						2,
						636.363636363636
					]
				],
				"typeOfSection": 0,
				"lengthInSteps": 16,
				"gfSection": false,
				"altAnim": false,
				"mustHitSection": false,
				"changeBPM": false,
				"bpm": 150
			},
			{
				"lengthInSteps": 16,
				"typeOfSection": 0,
				"sectionNotes": [
					[
						153309.090909091,
						7,
						90.9090909090909
					],
					[
						153490.909090909,
						4,
						90.9090909090909
					],
					[
						153672.727272727,
						6,
						90.9090909090909
					],
					[
						153854.545454545,
						5,
						90.9090909090909
					],
					[
						154036.363636363,
						7,
						272.727272727273
					],
					[
						154400,
						4,
						272.727272727273
					],
					[
						153309.090909091,
						0,
						90.9090909090909
					],
					[
						153490.909090909,
						2,
						90.9090909090909
					],
					[
						153672.727272727,
						0,
						90.9090909090909
					],
					[
						153854.545454545,
						1,
						90.9090909090909
					],
					[
						154036.363636363,
						3,
						636.363636363636
					]
				],
				"altAnim": false,
				"gfSection": false,
				"bpm": 150,
				"changeBPM": false,
				"mustHitSection": false
			},
			{
				"lengthInSteps": 16,
				"typeOfSection": 0,
				"sectionNotes": [
					[
						154763.636363636,
						5,
						818.181818181818
					],
					[
						154763.636363636,
						1,
						818.181818181818
					]
				],
				"altAnim": false,
				"gfSection": false,
				"bpm": 150,
				"changeBPM": false,
				"mustHitSection": false
			},
			{
				"lengthInSteps": 16,
				"typeOfSection": 0,
				"sectionNotes": [],
				"altAnim": false,
				"gfSection": false,
				"bpm": 150,
				"changeBPM": false,
				"mustHitSection": false
			},
			{
				"sectionNotes": [],
				"typeOfSection": 0,
				"lengthInSteps": 16,
				"gfSection": false,
				"altAnim": false,
				"mustHitSection": false,
				"changeBPM": false,
				"bpm": 150
			},
			{
				"lengthInSteps": 16,
				"typeOfSection": 0,
				"sectionNotes": [],
				"altAnim": false,
				"gfSection": false,
				"bpm": 150,
				"changeBPM": false,
				"mustHitSection": false
			},
			{
				"lengthInSteps": 16,
				"typeOfSection": 0,
				"sectionNotes": [],
				"altAnim": false,
				"gfSection": false,
				"bpm": 150,
				"changeBPM": false,
				"mustHitSection": true
			},
			{
				"lengthInSteps": 16,
				"typeOfSection": 0,
				"sectionNotes": [],
				"altAnim": false,
				"gfSection": false,
				"bpm": 150,
				"changeBPM": false,
				"mustHitSection": true
			},
			{
				"lengthInSteps": 16,
				"typeOfSection": 0,
				"sectionNotes": [],
				"altAnim": false,
				"gfSection": false,
				"bpm": 150,
				"changeBPM": false,
				"mustHitSection": true
			},
			{
				"lengthInSteps": 16,
				"typeOfSection": 0,
				"sectionNotes": [],
				"altAnim": false,
				"gfSection": false,
				"bpm": 150,
				"changeBPM": false,
				"mustHitSection": true
			},
			{
				"lengthInSteps": 16,
				"typeOfSection": 0,
				"sectionNotes": [],
				"altAnim": false,
				"gfSection": false,
				"bpm": 150,
				"changeBPM": false,
				"mustHitSection": true
			},
			{
				"lengthInSteps": 16,
				"typeOfSection": 0,
				"sectionNotes": [],
				"altAnim": false,
				"gfSection": false,
				"bpm": 150,
				"changeBPM": false,
				"mustHitSection": true
			},
			{
				"lengthInSteps": 16,
				"typeOfSection": 0,
				"sectionNotes": [],
				"altAnim": false,
				"gfSection": false,
				"bpm": 150,
				"changeBPM": false,
				"mustHitSection": true
			},
			{
				"lengthInSteps": 16,
				"typeOfSection": 0,
				"sectionNotes": [],
				"altAnim": false,
				"gfSection": false,
				"bpm": 150,
				"changeBPM": false,
				"mustHitSection": true
			},
			{
				"lengthInSteps": 16,
				"typeOfSection": 0,
				"sectionNotes": [],
				"altAnim": false,
				"gfSection": false,
				"bpm": 150,
				"changeBPM": false,
				"mustHitSection": true
			},
			{
				"sectionNotes": [],
				"typeOfSection": 0,
				"lengthInSteps": 16,
				"gfSection": false,
				"altAnim": false,
				"mustHitSection": true,
				"changeBPM": false,
				"bpm": 150
			},
			{
				"sectionNotes": [],
				"typeOfSection": 0,
				"lengthInSteps": 16,
				"gfSection": false,
				"altAnim": false,
				"mustHitSection": true,
				"changeBPM": false,
				"bpm": 150
			},
			{
				"sectionNotes": [],
				"typeOfSection": 0,
				"lengthInSteps": 16,
				"gfSection": false,
				"altAnim": false,
				"mustHitSection": true,
				"changeBPM": false,
				"bpm": 150
			},
			{
				"sectionNotes": [],
				"typeOfSection": 0,
				"lengthInSteps": 16,
				"gfSection": false,
				"altAnim": false,
				"mustHitSection": true,
				"changeBPM": false,
				"bpm": 150
			},
			{
				"sectionNotes": [],
				"typeOfSection": 0,
				"lengthInSteps": 16,
				"gfSection": false,
				"altAnim": false,
				"mustHitSection": true,
				"changeBPM": false,
				"bpm": 150
			},
			{
				"sectionNotes": [],
				"typeOfSection": 0,
				"lengthInSteps": 16,
				"gfSection": false,
				"altAnim": false,
				"mustHitSection": true,
				"changeBPM": false,
				"bpm": 150
			},
			{
				"sectionNotes": [],
				"typeOfSection": 0,
				"lengthInSteps": 16,
				"gfSection": false,
				"altAnim": false,
				"mustHitSection": true,
				"changeBPM": false,
				"bpm": 150
			},
			{
				"sectionNotes": [],
				"typeOfSection": 0,
				"lengthInSteps": 16,
				"gfSection": false,
				"altAnim": false,
				"mustHitSection": true,
				"changeBPM": false,
				"bpm": 150
			},
			{
				"sectionNotes": [],
				"typeOfSection": 0,
				"lengthInSteps": 16,
				"gfSection": false,
				"altAnim": false,
				"mustHitSection": true,
				"changeBPM": false,
				"bpm": 150
			},
			{
				"sectionNotes": [],
				"typeOfSection": 0,
				"lengthInSteps": 16,
				"gfSection": false,
				"altAnim": false,
				"mustHitSection": true,
				"changeBPM": false,
				"bpm": 150
			},
			{
				"sectionNotes": [],
				"typeOfSection": 0,
				"lengthInSteps": 16,
				"gfSection": false,
				"altAnim": false,
				"mustHitSection": true,
				"changeBPM": false,
				"bpm": 150
			},
			{
				"sectionNotes": [],
				"typeOfSection": 0,
				"lengthInSteps": 16,
				"gfSection": false,
				"altAnim": false,
				"mustHitSection": true,
				"changeBPM": false,
				"bpm": 150
			},
			{
				"lengthInSteps": 16,
				"typeOfSection": 0,
				"sectionNotes": [],
				"altAnim": false,
				"gfSection": false,
				"bpm": 150,
				"changeBPM": false,
				"mustHitSection": true
			},
			{
				"lengthInSteps": 16,
				"typeOfSection": 0,
				"sectionNotes": [],
				"altAnim": false,
				"gfSection": false,
				"bpm": 150,
				"changeBPM": false,
				"mustHitSection": true
			},
			{
				"lengthInSteps": 16,
				"typeOfSection": 0,
				"sectionNotes": [],
				"altAnim": false,
				"gfSection": false,
				"bpm": 150,
				"changeBPM": false,
				"mustHitSection": true
			},
			{
				"lengthInSteps": 16,
				"typeOfSection": 0,
				"sectionNotes": [],
				"altAnim": false,
				"gfSection": false,
				"bpm": 150,
				"changeBPM": false,
				"mustHitSection": true
			},
			{
				"lengthInSteps": 16,
				"typeOfSection": 0,
				"sectionNotes": [],
				"altAnim": false,
				"gfSection": false,
				"bpm": 150,
				"changeBPM": false,
				"mustHitSection": true
			},
			{
				"lengthInSteps": 16,
				"typeOfSection": 0,
				"sectionNotes": [],
				"altAnim": false,
				"gfSection": false,
				"bpm": 150,
				"changeBPM": false,
				"mustHitSection": true
			},
			{
				"lengthInSteps": 16,
				"typeOfSection": 0,
				"sectionNotes": [],
				"altAnim": false,
				"gfSection": false,
				"bpm": 150,
				"changeBPM": false,
				"mustHitSection": true
			},
			{
				"lengthInSteps": 16,
				"typeOfSection": 0,
				"sectionNotes": [],
				"altAnim": false,
				"gfSection": false,
				"bpm": 150,
				"changeBPM": false,
				"mustHitSection": true
			},
			{
				"lengthInSteps": 16,
				"typeOfSection": 0,
				"sectionNotes": [],
				"altAnim": false,
				"gfSection": false,
				"bpm": 150,
				"changeBPM": false,
				"mustHitSection": true
			},
			{
				"lengthInSteps": 16,
				"typeOfSection": 0,
				"sectionNotes": [],
				"altAnim": false,
				"gfSection": false,
				"bpm": 150,
				"changeBPM": false,
				"mustHitSection": true
			},
			{
				"lengthInSteps": 16,
				"typeOfSection": 0,
				"sectionNotes": [],
				"altAnim": false,
				"gfSection": false,
				"bpm": 150,
				"changeBPM": false,
				"mustHitSection": true
			},
			{
				"lengthInSteps": 16,
				"typeOfSection": 0,
				"sectionNotes": [],
				"altAnim": false,
				"gfSection": false,
				"bpm": 150,
				"changeBPM": false,
				"mustHitSection": true
			},
			{
				"sectionNotes": [],
				"typeOfSection": 0,
				"lengthInSteps": 16,
				"gfSection": false,
				"altAnim": false,
				"mustHitSection": true,
				"changeBPM": false,
				"bpm": 150
			},
			{
				"sectionNotes": [],
				"typeOfSection": 0,
				"lengthInSteps": 16,
				"gfSection": false,
				"altAnim": false,
				"mustHitSection": true,
				"changeBPM": false,
				"bpm": 150
			},
			{
				"sectionNotes": [],
				"typeOfSection": 0,
				"lengthInSteps": 16,
				"gfSection": false,
				"altAnim": false,
				"mustHitSection": true,
				"changeBPM": false,
				"bpm": 150
			},
			{
				"sectionNotes": [],
				"typeOfSection": 0,
				"lengthInSteps": 16,
				"gfSection": false,
				"altAnim": false,
				"mustHitSection": true,
				"changeBPM": false,
				"bpm": 150
			},
			{
				"sectionNotes": [],
				"typeOfSection": 0,
				"lengthInSteps": 16,
				"gfSection": false,
				"altAnim": false,
				"mustHitSection": true,
				"changeBPM": false,
				"bpm": 150
			},
			{
				"sectionNotes": [],
				"typeOfSection": 0,
				"lengthInSteps": 16,
				"gfSection": false,
				"altAnim": false,
				"mustHitSection": true,
				"changeBPM": false,
				"bpm": 150
			},
			{
				"sectionNotes": [],
				"typeOfSection": 0,
				"lengthInSteps": 16,
				"gfSection": false,
				"altAnim": false,
				"mustHitSection": true,
				"changeBPM": false,
				"bpm": 150
			},
			{
				"sectionNotes": [],
				"typeOfSection": 0,
				"lengthInSteps": 16,
				"gfSection": false,
				"altAnim": false,
				"mustHitSection": true,
				"changeBPM": false,
				"bpm": 150
			},
			{
				"sectionNotes": [],
				"typeOfSection": 0,
				"lengthInSteps": 16,
				"gfSection": false,
				"altAnim": false,
				"mustHitSection": true,
				"changeBPM": false,
				"bpm": 150
			},
			{
				"sectionNotes": [],
				"typeOfSection": 0,
				"lengthInSteps": 16,
				"gfSection": false,
				"altAnim": false,
				"mustHitSection": true,
				"changeBPM": false,
				"bpm": 150
			},
			{
				"sectionNotes": [],
				"typeOfSection": 0,
				"lengthInSteps": 16,
				"gfSection": false,
				"altAnim": false,
				"mustHitSection": true,
				"changeBPM": false,
				"bpm": 150
			},
			{
				"sectionNotes": [],
				"typeOfSection": 0,
				"lengthInSteps": 16,
				"gfSection": false,
				"altAnim": false,
				"mustHitSection": true,
				"changeBPM": false,
				"bpm": 150
			},
			{
				"sectionNotes": [],
				"typeOfSection": 0,
				"lengthInSteps": 16,
				"gfSection": false,
				"altAnim": false,
				"mustHitSection": true,
				"changeBPM": false,
				"bpm": 150
			},
			{
				"sectionNotes": [],
				"typeOfSection": 0,
				"lengthInSteps": 16,
				"gfSection": false,
				"altAnim": false,
				"mustHitSection": true,
				"changeBPM": false,
				"bpm": 150
			},
			{
				"sectionNotes": [],
				"typeOfSection": 0,
				"lengthInSteps": 16,
				"gfSection": false,
				"altAnim": false,
				"mustHitSection": true,
				"changeBPM": false,
				"bpm": 150
			},
			{
				"sectionNotes": [],
				"typeOfSection": 0,
				"lengthInSteps": 16,
				"gfSection": false,
				"altAnim": false,
				"mustHitSection": true,
				"changeBPM": false,
				"bpm": 150
			},
			{
				"sectionNotes": [],
				"typeOfSection": 0,
				"lengthInSteps": 16,
				"gfSection": false,
				"altAnim": false,
				"mustHitSection": true,
				"changeBPM": false,
				"bpm": 150
			},
			{
				"sectionNotes": [],
				"typeOfSection": 0,
				"lengthInSteps": 16,
				"gfSection": false,
				"altAnim": false,
				"mustHitSection": true,
				"changeBPM": false,
				"bpm": 150
			},
			{
				"sectionNotes": [],
				"typeOfSection": 0,
				"lengthInSteps": 16,
				"gfSection": false,
				"altAnim": false,
				"mustHitSection": true,
				"changeBPM": false,
				"bpm": 150
			},
			{
				"sectionNotes": [],
				"typeOfSection": 0,
				"lengthInSteps": 16,
				"gfSection": false,
				"altAnim": false,
				"mustHitSection": true,
				"changeBPM": false,
				"bpm": 150
			},
			{
				"sectionNotes": [],
				"typeOfSection": 0,
				"lengthInSteps": 16,
				"gfSection": false,
				"altAnim": false,
				"mustHitSection": true,
				"changeBPM": false,
				"bpm": 150
			},
			{
				"sectionNotes": [],
				"typeOfSection": 0,
				"lengthInSteps": 16,
				"gfSection": false,
				"altAnim": false,
				"mustHitSection": true,
				"changeBPM": false,
				"bpm": 150
			},
			{
				"sectionNotes": [],
				"typeOfSection": 0,
				"lengthInSteps": 16,
				"gfSection": false,
				"altAnim": false,
				"mustHitSection": true,
				"changeBPM": false,
				"bpm": 150
			},
			{
				"sectionNotes": [],
				"typeOfSection": 0,
				"lengthInSteps": 16,
				"gfSection": false,
				"altAnim": false,
				"mustHitSection": true,
				"changeBPM": false,
				"bpm": 150
			},
			{
				"sectionNotes": [],
				"typeOfSection": 0,
				"lengthInSteps": 16,
				"gfSection": false,
				"altAnim": false,
				"mustHitSection": true,
				"changeBPM": false,
				"bpm": 150
			},
			{
				"sectionNotes": [],
				"typeOfSection": 0,
				"lengthInSteps": 16,
				"gfSection": false,
				"altAnim": false,
				"mustHitSection": true,
				"changeBPM": false,
				"bpm": 150
			},
			{
				"sectionNotes": [],
				"typeOfSection": 0,
				"lengthInSteps": 16,
				"gfSection": false,
				"altAnim": false,
				"mustHitSection": true,
				"changeBPM": false,
				"bpm": 150
			},
			{
				"sectionNotes": [],
				"typeOfSection": 0,
				"lengthInSteps": 16,
				"gfSection": false,
				"altAnim": false,
				"mustHitSection": true,
				"changeBPM": false,
				"bpm": 150
			},
			{
				"sectionNotes": [],
				"typeOfSection": 0,
				"lengthInSteps": 16,
				"gfSection": false,
				"altAnim": false,
				"mustHitSection": true,
				"changeBPM": false,
				"bpm": 150
			},
			{
				"sectionNotes": [],
				"typeOfSection": 0,
				"lengthInSteps": 16,
				"gfSection": false,
				"altAnim": false,
				"mustHitSection": true,
				"changeBPM": false,
				"bpm": 150
			},
			{
				"sectionNotes": [],
				"typeOfSection": 0,
				"lengthInSteps": 16,
				"gfSection": false,
				"altAnim": false,
				"mustHitSection": true,
				"changeBPM": false,
				"bpm": 150
			},
			{
				"sectionNotes": [],
				"typeOfSection": 0,
				"lengthInSteps": 16,
				"gfSection": false,
				"altAnim": false,
				"mustHitSection": true,
				"changeBPM": false,
				"bpm": 150
			},
			{
				"sectionNotes": [],
				"typeOfSection": 0,
				"lengthInSteps": 16,
				"gfSection": false,
				"altAnim": false,
				"mustHitSection": true,
				"changeBPM": false,
				"bpm": 150
			},
			{
				"sectionNotes": [],
				"typeOfSection": 0,
				"lengthInSteps": 16,
				"gfSection": false,
				"altAnim": false,
				"mustHitSection": true,
				"changeBPM": false,
				"bpm": 150
			},
			{
				"sectionNotes": [],
				"typeOfSection": 0,
				"lengthInSteps": 16,
				"gfSection": false,
				"altAnim": false,
				"mustHitSection": true,
				"changeBPM": false,
				"bpm": 150
			},
			{
				"sectionNotes": [],
				"typeOfSection": 0,
				"lengthInSteps": 16,
				"gfSection": false,
				"altAnim": false,
				"mustHitSection": true,
				"changeBPM": false,
				"bpm": 150
			},
			{
				"sectionNotes": [],
				"typeOfSection": 0,
				"lengthInSteps": 16,
				"gfSection": false,
				"altAnim": false,
				"mustHitSection": true,
				"changeBPM": false,
				"bpm": 150
			},
			{
				"sectionNotes": [],
				"typeOfSection": 0,
				"lengthInSteps": 16,
				"gfSection": false,
				"altAnim": false,
				"mustHitSection": true,
				"changeBPM": false,
				"bpm": 150
			},
			{
				"sectionNotes": [],
				"typeOfSection": 0,
				"lengthInSteps": 16,
				"gfSection": false,
				"altAnim": false,
				"mustHitSection": true,
				"changeBPM": false,
				"bpm": 150
			},
			{
				"sectionNotes": [],
				"typeOfSection": 0,
				"lengthInSteps": 16,
				"gfSection": false,
				"altAnim": false,
				"mustHitSection": true,
				"changeBPM": false,
				"bpm": 150
			},
			{
				"sectionNotes": [],
				"typeOfSection": 0,
				"lengthInSteps": 16,
				"gfSection": false,
				"altAnim": false,
				"mustHitSection": true,
				"changeBPM": false,
				"bpm": 150
			},
			{
				"sectionNotes": [],
				"typeOfSection": 0,
				"lengthInSteps": 16,
				"gfSection": false,
				"altAnim": false,
				"mustHitSection": true,
				"changeBPM": false,
				"bpm": 150
			},
			{
				"sectionNotes": [],
				"typeOfSection": 0,
				"lengthInSteps": 16,
				"gfSection": false,
				"altAnim": false,
				"mustHitSection": true,
				"changeBPM": false,
				"bpm": 150
			},
			{
				"sectionNotes": [],
				"typeOfSection": 0,
				"lengthInSteps": 16,
				"gfSection": false,
				"altAnim": false,
				"mustHitSection": true,
				"changeBPM": false,
				"bpm": 150
			},
			{
				"sectionNotes": [],
				"typeOfSection": 0,
				"lengthInSteps": 16,
				"gfSection": false,
				"altAnim": false,
				"mustHitSection": true,
				"changeBPM": false,
				"bpm": 150
			},
			{
				"sectionNotes": [],
				"typeOfSection": 0,
				"lengthInSteps": 16,
				"gfSection": false,
				"altAnim": false,
				"mustHitSection": true,
				"changeBPM": false,
				"bpm": 150
			},
			{
				"sectionNotes": [],
				"typeOfSection": 0,
				"lengthInSteps": 16,
				"gfSection": false,
				"altAnim": false,
				"mustHitSection": true,
				"changeBPM": false,
				"bpm": 150
			},
			{
				"sectionNotes": [],
				"typeOfSection": 0,
				"lengthInSteps": 16,
				"gfSection": false,
				"altAnim": false,
				"mustHitSection": true,
				"changeBPM": false,
				"bpm": 150
			},
			{
				"sectionNotes": [],
				"typeOfSection": 0,
				"lengthInSteps": 16,
				"gfSection": false,
				"altAnim": false,
				"mustHitSection": true,
				"changeBPM": false,
				"bpm": 150
			},
			{
				"sectionNotes": [],
				"typeOfSection": 0,
				"lengthInSteps": 16,
				"gfSection": false,
				"altAnim": false,
				"mustHitSection": true,
				"changeBPM": false,
				"bpm": 150
			},
			{
				"sectionNotes": [],
				"typeOfSection": 0,
				"lengthInSteps": 16,
				"gfSection": false,
				"altAnim": false,
				"mustHitSection": true,
				"changeBPM": false,
				"bpm": 150
			},
			{
				"sectionNotes": [],
				"typeOfSection": 0,
				"lengthInSteps": 16,
				"gfSection": false,
				"altAnim": false,
				"mustHitSection": true,
				"changeBPM": false,
				"bpm": 150
			},
			{
				"sectionNotes": [],
				"typeOfSection": 0,
				"lengthInSteps": 16,
				"gfSection": false,
				"altAnim": false,
				"mustHitSection": true,
				"changeBPM": false,
				"bpm": 150
			},
			{
				"sectionNotes": [],
				"typeOfSection": 0,
				"lengthInSteps": 16,
				"gfSection": false,
				"altAnim": false,
				"mustHitSection": true,
				"changeBPM": false,
				"bpm": 150
			},
			{
				"lengthInSteps": 16,
				"typeOfSection": 0,
				"sectionNotes": [],
				"altAnim": false,
				"gfSection": false,
				"bpm": 150,
				"changeBPM": false,
				"mustHitSection": true
			},
			{
				"lengthInSteps": 16,
				"typeOfSection": 0,
				"sectionNotes": [],
				"altAnim": false,
				"gfSection": false,
				"bpm": 150,
				"changeBPM": false,
				"mustHitSection": true
			},
			{
				"lengthInSteps": 16,
				"typeOfSection": 0,
				"sectionNotes": [],
				"altAnim": false,
				"gfSection": false,
				"bpm": 150,
				"changeBPM": false,
				"mustHitSection": true
			},
			{
				"lengthInSteps": 16,
				"typeOfSection": 0,
				"sectionNotes": [],
				"altAnim": false,
				"gfSection": false,
				"bpm": 150,
				"changeBPM": false,
				"mustHitSection": true
			},
			{
				"lengthInSteps": 16,
				"typeOfSection": 0,
				"sectionNotes": [],
				"altAnim": false,
				"gfSection": false,
				"bpm": 150,
				"changeBPM": false,
				"mustHitSection": true
			},
			{
				"lengthInSteps": 16,
				"typeOfSection": 0,
				"sectionNotes": [],
				"altAnim": false,
				"gfSection": false,
				"bpm": 150,
				"changeBPM": false,
				"mustHitSection": true
			},
			{
				"lengthInSteps": 16,
				"typeOfSection": 0,
				"sectionNotes": [],
				"altAnim": false,
				"gfSection": false,
				"bpm": 150,
				"changeBPM": false,
				"mustHitSection": true
			},
			{
				"lengthInSteps": 16,
				"typeOfSection": 0,
				"sectionNotes": [],
				"altAnim": false,
				"gfSection": false,
				"bpm": 150,
				"changeBPM": false,
				"mustHitSection": true
			},
			{
				"lengthInSteps": 16,
				"typeOfSection": 0,
				"sectionNotes": [],
				"altAnim": false,
				"gfSection": false,
				"bpm": 150,
				"changeBPM": false,
				"mustHitSection": true
			},
			{
				"lengthInSteps": 16,
				"typeOfSection": 0,
				"sectionNotes": [],
				"altAnim": false,
				"gfSection": false,
				"bpm": 150,
				"changeBPM": false,
				"mustHitSection": true
			},
			{
				"lengthInSteps": 16,
				"typeOfSection": 0,
				"sectionNotes": [],
				"altAnim": false,
				"gfSection": false,
				"bpm": 150,
				"changeBPM": false,
				"mustHitSection": true
			},
			{
				"lengthInSteps": 16,
				"typeOfSection": 0,
				"sectionNotes": [],
				"altAnim": false,
				"gfSection": false,
				"bpm": 150,
				"changeBPM": false,
				"mustHitSection": true
			},
			{
				"lengthInSteps": 16,
				"typeOfSection": 0,
				"sectionNotes": [],
				"altAnim": false,
				"gfSection": false,
				"bpm": 150,
				"changeBPM": false,
				"mustHitSection": true
			},
			{
				"lengthInSteps": 16,
				"typeOfSection": 0,
				"sectionNotes": [],
				"altAnim": false,
				"gfSection": false,
				"bpm": 150,
				"changeBPM": false,
				"mustHitSection": true
			},
			{
				"lengthInSteps": 16,
				"typeOfSection": 0,
				"sectionNotes": [],
				"altAnim": false,
				"gfSection": false,
				"bpm": 150,
				"changeBPM": false,
				"mustHitSection": true
			},
			{
				"sectionNotes": [],
				"typeOfSection": 0,
				"lengthInSteps": 16,
				"gfSection": false,
				"altAnim": false,
				"mustHitSection": true,
				"changeBPM": false,
				"bpm": 150
			},
			{
				"sectionNotes": [],
				"typeOfSection": 0,
				"lengthInSteps": 16,
				"gfSection": false,
				"altAnim": false,
				"mustHitSection": true,
				"changeBPM": false,
				"bpm": 150
			},
			{
				"sectionNotes": [],
				"typeOfSection": 0,
				"lengthInSteps": 16,
				"gfSection": false,
				"altAnim": false,
				"mustHitSection": true,
				"changeBPM": false,
				"bpm": 150
			},
			{
				"sectionNotes": [],
				"typeOfSection": 0,
				"lengthInSteps": 16,
				"gfSection": false,
				"altAnim": false,
				"mustHitSection": true,
				"changeBPM": false,
				"bpm": 150
			},
			{
				"lengthInSteps": 16,
				"typeOfSection": 0,
				"sectionNotes": [],
				"altAnim": false,
				"gfSection": false,
				"bpm": 150,
				"changeBPM": false,
				"mustHitSection": true
			},
			{
				"sectionNotes": [],
				"typeOfSection": 0,
				"lengthInSteps": 16,
				"gfSection": false,
				"altAnim": false,
				"mustHitSection": true,
				"changeBPM": false,
				"bpm": 150
			},
			{
				"sectionNotes": [],
				"typeOfSection": 0,
				"lengthInSteps": 16,
				"gfSection": false,
				"altAnim": false,
				"mustHitSection": true,
				"changeBPM": false,
				"bpm": 150
			},
			{
				"sectionNotes": [],
				"typeOfSection": 0,
				"lengthInSteps": 16,
				"gfSection": false,
				"altAnim": false,
				"mustHitSection": true,
				"changeBPM": false,
				"bpm": 150
			},
			{
				"sectionNotes": [],
				"typeOfSection": 0,
				"lengthInSteps": 16,
				"gfSection": false,
				"altAnim": false,
				"mustHitSection": true,
				"changeBPM": false,
				"bpm": 150
			},
			{
				"sectionNotes": [],
				"typeOfSection": 0,
				"lengthInSteps": 16,
				"gfSection": false,
				"altAnim": false,
				"mustHitSection": true,
				"changeBPM": false,
				"bpm": 150
			},
			{
				"sectionNotes": [],
				"typeOfSection": 0,
				"lengthInSteps": 16,
				"gfSection": false,
				"altAnim": false,
				"mustHitSection": true,
				"changeBPM": false,
				"bpm": 150
			},
			{
				"sectionNotes": [],
				"typeOfSection": 0,
				"lengthInSteps": 16,
				"gfSection": false,
				"altAnim": false,
				"mustHitSection": true,
				"changeBPM": false,
				"bpm": 150
			},
			{
				"sectionNotes": [],
				"typeOfSection": 0,
				"lengthInSteps": 16,
				"gfSection": false,
				"altAnim": false,
				"mustHitSection": true,
				"changeBPM": false,
				"bpm": 150
			},
			{
				"sectionNotes": [],
				"typeOfSection": 0,
				"lengthInSteps": 16,
				"gfSection": false,
				"altAnim": false,
				"mustHitSection": true,
				"changeBPM": false,
				"bpm": 150
			},
			{
				"sectionNotes": [],
				"typeOfSection": 0,
				"lengthInSteps": 16,
				"gfSection": false,
				"altAnim": false,
				"mustHitSection": true,
				"changeBPM": false,
				"bpm": 150
			},
			{
				"sectionNotes": [],
				"typeOfSection": 0,
				"lengthInSteps": 16,
				"gfSection": false,
				"altAnim": false,
				"mustHitSection": true,
				"changeBPM": false,
				"bpm": 150
			},
			{
				"sectionNotes": [],
				"typeOfSection": 0,
				"lengthInSteps": 16,
				"gfSection": false,
				"altAnim": false,
				"mustHitSection": true,
				"changeBPM": false,
				"bpm": 150
			},
			{
				"lengthInSteps": 16,
				"typeOfSection": 0,
				"sectionNotes": [],
				"altAnim": false,
				"gfSection": false,
				"bpm": 150,
				"changeBPM": false,
				"mustHitSection": true
			},
			{
				"lengthInSteps": 16,
				"typeOfSection": 0,
				"sectionNotes": [],
				"altAnim": false,
				"gfSection": false,
				"bpm": 150,
				"changeBPM": false,
				"mustHitSection": true
			},
			{
				"lengthInSteps": 16,
				"typeOfSection": 0,
				"sectionNotes": [],
				"altAnim": false,
				"gfSection": false,
				"bpm": 150,
				"changeBPM": false,
				"mustHitSection": true
			},
			{
				"lengthInSteps": 16,
				"typeOfSection": 0,
				"sectionNotes": [],
				"altAnim": false,
				"gfSection": false,
				"bpm": 150,
				"changeBPM": false,
				"mustHitSection": true
			},
			{
				"lengthInSteps": 16,
				"typeOfSection": 0,
				"sectionNotes": [],
				"altAnim": false,
				"gfSection": false,
				"bpm": 150,
				"changeBPM": false,
				"mustHitSection": true
			},
			{
				"lengthInSteps": 16,
				"typeOfSection": 0,
				"sectionNotes": [],
				"altAnim": false,
				"gfSection": false,
				"bpm": 150,
				"changeBPM": false,
				"mustHitSection": true
			},
			{
				"lengthInSteps": 16,
				"typeOfSection": 0,
				"sectionNotes": [],
				"altAnim": false,
				"gfSection": false,
				"bpm": 150,
				"changeBPM": false,
				"mustHitSection": true
			},
			{
				"sectionNotes": [],
				"typeOfSection": 0,
				"lengthInSteps": 16,
				"gfSection": false,
				"altAnim": false,
				"mustHitSection": true,
				"changeBPM": false,
				"bpm": 150
			},
			{
				"lengthInSteps": 16,
				"typeOfSection": 0,
				"sectionNotes": [],
				"altAnim": false,
				"gfSection": false,
				"bpm": 150,
				"changeBPM": false,
				"mustHitSection": true
			},
			{
				"lengthInSteps": 16,
				"typeOfSection": 0,
				"sectionNotes": [],
				"altAnim": false,
				"gfSection": false,
				"bpm": 150,
				"changeBPM": false,
				"mustHitSection": true
			},
			{
				"sectionNotes": [],
				"typeOfSection": 0,
				"lengthInSteps": 16,
				"gfSection": false,
				"altAnim": false,
				"mustHitSection": true,
				"changeBPM": false,
				"bpm": 150
			},
			{
				"sectionNotes": [],
				"typeOfSection": 0,
				"lengthInSteps": 16,
				"gfSection": false,
				"altAnim": false,
				"mustHitSection": true,
				"changeBPM": false,
				"bpm": 150
			},
			{
				"lengthInSteps": 16,
				"typeOfSection": 0,
				"sectionNotes": [],
				"altAnim": false,
				"gfSection": false,
				"bpm": 150,
				"changeBPM": false,
				"mustHitSection": true
			},
			{
				"lengthInSteps": 16,
				"typeOfSection": 0,
				"sectionNotes": [],
				"altAnim": false,
				"gfSection": false,
				"bpm": 150,
				"changeBPM": false,
				"mustHitSection": true
			},
			{
				"lengthInSteps": 16,
				"typeOfSection": 0,
				"sectionNotes": [],
				"altAnim": false,
				"gfSection": false,
				"bpm": 150,
				"changeBPM": false,
				"mustHitSection": true
			},
			{
				"sectionBeats": 4,
				"sectionNotes": [],
				"typeOfSection": 0,
				"gfSection": false,
				"altAnim": false,
				"mustHitSection": true,
				"changeBPM": false,
				"bpm": 150
			},
			{
				"typeOfSection": 0,
				"sectionNotes": [],
				"sectionBeats": 4,
				"altAnim": false,
				"gfSection": false,
				"bpm": 150,
				"changeBPM": false,
				"mustHitSection": true
			},
			{
				"sectionBeats": 4,
				"sectionNotes": [],
				"typeOfSection": 0,
				"gfSection": false,
				"altAnim": false,
				"mustHitSection": true,
				"changeBPM": false,
				"bpm": 150
			},
			{
				"sectionBeats": 4,
				"sectionNotes": [],
				"typeOfSection": 0,
				"gfSection": false,
				"altAnim": false,
				"mustHitSection": true,
				"changeBPM": false,
				"bpm": 150
			},
			{
				"typeOfSection": 0,
				"sectionNotes": [],
				"sectionBeats": 4,
				"altAnim": false,
				"gfSection": false,
				"bpm": 150,
				"changeBPM": false,
				"mustHitSection": true
			},
			{
				"sectionBeats": 4,
				"sectionNotes": [],
				"typeOfSection": 0,
				"gfSection": false,
				"altAnim": false,
				"mustHitSection": true,
				"changeBPM": false,
				"bpm": 150
			},
			{
				"gfSection": false,
				"altAnim": false,
				"typeOfSection": 0,
				"sectionNotes": [],
				"bpm": 150,
				"sectionBeats": 4,
				"changeBPM": false,
				"mustHitSection": true
			},
			{
				"gfSection": false,
				"altAnim": false,
				"typeOfSection": 0,
				"sectionNotes": [],
				"bpm": 150,
				"sectionBeats": 4,
				"changeBPM": false,
				"mustHitSection": true
			}
		],
		"player2": "Henry",
		"player3": null,
		"song": "isolation",
		"needsVoices": true,
		"validScore": true,
		"stage": "henryroom",
		"bpm": 150,
		"speed": 2.3
	}
}